django_vcache/__init__.py
django_vcache/backend.py
django_vcache/utils.py
django_vcache/wsgi.py
django_vcache-0.1.3.dist-info/METADATA
django_vcache-0.1.3.dist-info/WHEEL
django_vcache-0.1.3.dist-info/licenses/LICENSE
django_vcache-0.1.3.dist-info/RECORD
