Metadata-Version: 2.4
Name: django-vcache
Version: 0.1.3
Summary: A specialized, lightweight Django cache backend for Valkey.
Project-URL: Homepage, https://gitlab.com/glitchtip/django-vcache
Project-URL: Bug Tracker, https://gitlab.com/glitchtip/django-vcache/issues
Author-email: David Burke <david@burkesoftware.com>
License: MIT License
License-File: LICENSE
Classifier: Development Status :: 4 - Beta
Classifier: Framework :: Django
Classifier: Framework :: Django :: 6.0
Classifier: Intended Audience :: Developers
Classifier: License :: OSI Approved :: MIT License
Classifier: Operating System :: OS Independent
Classifier: Programming Language :: Python
Classifier: Programming Language :: Python :: 3
Classifier: Programming Language :: Python :: 3.12
Classifier: Topic :: Software Development :: Libraries :: Python Modules
Requires-Python: >=3.12
Requires-Dist: django>=5.0
Requires-Dist: valkey[libvalkey]
Requires-Dist: zstd; python_version < '3.14'
